CHANGES
LICENSE
README.txt
bootstrap.py
buildout.cfg
setup.cfg
setup.py
iw/__init__.py
iw.eggproxy.egg-info/PKG-INFO
iw.eggproxy.egg-info/SOURCES.txt
iw.eggproxy.egg-info/dependency_links.txt
iw.eggproxy.egg-info/entry_points.txt
iw.eggproxy.egg-info/namespace_packages.txt
iw.eggproxy.egg-info/not-zip-safe
iw.eggproxy.egg-info/requires.txt
iw.eggproxy.egg-info/top_level.txt
iw/eggproxy/README.txt
iw/eggproxy/__init__.py
iw/eggproxy/apache_handler.py
iw/eggproxy/config.py
iw/eggproxy/update_script.py
iw/eggproxy/utils.py
iw/eggproxy/docs/README.txt
iw/eggproxy/doctests/README.txt
iw/eggproxy/tests/__init__.py
iw/eggproxy/tests/test_eggproxydocs.py
iw/eggproxy/tests/test_eggproxydocstrings.py