Metadata-Version: 1.0
Name: iw.eggproxy
Version: 0.2.0
Summary: An egg proxy for apache and mod_python
Home-page: https://ingeniweb.svn.sourceforge.net/svnroot/ingeniweb/iw.eggproxy
Author: Ingeniweb
Author-email: support@ingeniweb.com
License: GPL
Keywords: setuptools easy_install index proxy
Platform: UNKNOWN
Classifier: Programming Language :: Python
Classifier: Topic :: Software Development :: Libraries :: Python Modules
